COPYING
LICENSE
MANIFEST.in
README.rst
_bioinformatics.py
ez_setup.py
requirements.txt
setup.py
Orange_Bioinformatics.egg-info/PKG-INFO
Orange_Bioinformatics.egg-info/SOURCES.txt
Orange_Bioinformatics.egg-info/dependency_links.txt
Orange_Bioinformatics.egg-info/entry_points.txt
Orange_Bioinformatics.egg-info/namespace_packages.txt
Orange_Bioinformatics.egg-info/not-zip-safe
Orange_Bioinformatics.egg-info/requires.txt
Orange_Bioinformatics.egg-info/top_level.txt
docs/Makefile
orangecontrib/__init__.py
orangecontrib/bio/__init__.py
orangecontrib/bio/arrayexpress.py
orangecontrib/bio/biomart.py
orangecontrib/bio/chem.py
orangecontrib/bio/geo.py
orangecontrib/bio/go.py
orangecontrib/bio/gsea.py
orangecontrib/bio/mesh.py
orangecontrib/bio/obiArrayExpress.py
orangecontrib/bio/obiBioMart.py
orangecontrib/bio/obiChem.py
orangecontrib/bio/obiDicty.py
orangecontrib/bio/obiDictyMutants.py
orangecontrib/bio/obiExperiments.py
orangecontrib/bio/obiExpression.py
orangecontrib/bio/obiGEO.py
orangecontrib/bio/obiGO.py
orangecontrib/bio/obiGene.py
orangecontrib/bio/obiGeneAtlas.py
orangecontrib/bio/obiGeneMania.py
orangecontrib/bio/obiGeneSetSig.py
orangecontrib/bio/obiGeneSets.py
orangecontrib/bio/obiGsea.py
orangecontrib/bio/obiHomoloGene.py
orangecontrib/bio/obiKEGG.py
orangecontrib/bio/obiMeSH.py
orangecontrib/bio/obiOMIM.py
orangecontrib/bio/obiOntology.py
orangecontrib/bio/obiPPI.py
orangecontrib/bio/obiProb.py
orangecontrib/bio/obiTaxonomy.py
orangecontrib/bio/obimiRNA.py
orangecontrib/bio/omim.py
orangecontrib/bio/ontology.py
orangecontrib/bio/ppi.py
orangecontrib/bio/taxonomy.py
orangecontrib/bio/dicty/__init__.py
orangecontrib/bio/dicty/phenotypes.py
orangecontrib/bio/gene/__init__.py
orangecontrib/bio/gene/homology.py
orangecontrib/bio/geneset/__init__.py
orangecontrib/bio/geneset/transform.py
orangecontrib/bio/kegg/__init__.py
orangecontrib/bio/kegg/api.py
orangecontrib/bio/kegg/brite.py
orangecontrib/bio/kegg/caching.py
orangecontrib/bio/kegg/conf.py
orangecontrib/bio/kegg/databases.py
orangecontrib/bio/kegg/pathway.py
orangecontrib/bio/kegg/service.py
orangecontrib/bio/kegg/types.py
orangecontrib/bio/kegg/entry/__init__.py
orangecontrib/bio/kegg/entry/fields.py
orangecontrib/bio/kegg/entry/parser.py
orangecontrib/bio/kegg/tests/__init__.py
orangecontrib/bio/kegg/tests/test_api.py
orangecontrib/bio/kegg/tests/test_databases.py
