Metadata-Version: 1.1
Name: Orange-Bioinformatics
Version: 2.6.25
Summary: Orange Bioinformatics add-on for Orange data mining software package.
Home-page: http://orange.biolab.si/download
Author: Bioinformatics Laboratory, FRI UL
Author-email: contact@orange.biolab.si
License: GPLv3
Keywords: data mining,machine learning,artificial intelligence,bioinformatics,gene ontology,KEGG,expression profiles,microarray,genomics,orange,orange add-on
Platform: UNKNOWN
Classifier: Development Status :: 4 - Beta
Classifier: Environment :: X11 Applications :: Qt
Classifier: Environment :: Console
Classifier: Environment :: Plugins
Classifier: Programming Language :: Python
Classifier: License :: OSI Approved :: GNU General Public License v3 or later (GPLv3+)
Classifier: Operating System :: OS Independent
Classifier: Topic :: Scientific/Engineering :: Artificial Intelligence
Classifier: Topic :: Scientific/Engineering :: Visualization
Classifier: Topic :: Scientific/Engineering :: Bio-Informatics
Classifier: Topic :: Software Development :: Libraries :: Python Modules
Classifier: Intended Audience :: Education
Classifier: Intended Audience :: Science/Research
Classifier: Intended Audience :: Developers
